{
	"name": "mynotebook",
	"properties": {
		"nbformat": 4,
		"nbformat_minor": 2,
		"bigDataPool": {
			"referenceName": "SparkPool01",
			"type": "BigDataPoolReference"
		},
		"sessionProperties": {
			"driverMemory": "28g",
			"driverCores": 4,
			"executorMemory": "28g",
			"executorCores": 4,
			"numExecutors": 2,
			"conf": {
				"spark.dynamicAllocation.enabled": "false",
				"spark.dynamicAllocation.minExecutors": "2",
				"spark.dynamicAllocation.maxExecutors": "2"
			}
		},
		"metadata": {
			"saveOutput": true,
			"synapse_widget": {
				"version": "0.1"
			},
			"kernelspec": {
				"name": "synapse_pyspark",
				"display_name": "python"
			},
			"language_info": {
				"name": "python"
			},
			"a365ComputeOptions": {
				"id": "/subscriptions/7567b7de-befe-40fa-b883-40bb316ee50c/resourceGroups/Lab8/providers/Microsoft.Synapse/workspaces/asaworkspacelab8/bigDataPools/SparkPool01",
				"name": "SparkPool01",
				"type": "Spark",
				"endpoint": "https://asaworkspacelab8.dev.azuresynapse.net/livyApi/versions/2019-11-01-preview/sparkPools/SparkPool01",
				"auth": {
					"type": "AAD",
					"authResource": "https://dev.azuresynapse.net"
				},
				"sparkVersion": "2.4",
				"nodeCount": 3,
				"cores": 4,
				"memory": 28,
				"extraHeader": null
			}
		},
		"cells": [
			{
				"cell_type": "code",
				"source": [
					""
				],
				"attachments": null,
				"execution_count": null
			}
		]
	}
}